{
    "/js/app.js": "/js/app.js",
    "/js/settings-app.js": "/js/settings-app.js",
    "/js/app.661c4da6200b1b95398a.hot-update.js": "/js/app.661c4da6200b1b95398a.hot-update.js",
    "/js/app.e5e73edf4fbb65c7ac3a.hot-update.js": "/js/app.e5e73edf4fbb65c7ac3a.hot-update.js",
    "/js/app.0e2b3cfd75517f328c7e.hot-update.js": "/js/app.0e2b3cfd75517f328c7e.hot-update.js",
    "/js/app.d5b24fef4dea84f450e0.hot-update.js": "/js/app.d5b24fef4dea84f450e0.hot-update.js",
    "/js/app.bd345a49b611d2123743.hot-update.js": "/js/app.bd345a49b611d2123743.hot-update.js",
    "/js/app.2f067eb088880ab8d30b.hot-update.js": "/js/app.2f067eb088880ab8d30b.hot-update.js",
    "/js/app.6ec3065971da4ddb6c0a.hot-update.js": "/js/app.6ec3065971da4ddb6c0a.hot-update.js",
    "/js/app.b840ca6f09ed6d1acd41.hot-update.js": "/js/app.b840ca6f09ed6d1acd41.hot-update.js",
    "/js/app.a3801497f4493922dca4.hot-update.js": "/js/app.a3801497f4493922dca4.hot-update.js",
    "/js/app.7c5016c0d871f3a47082.hot-update.js": "/js/app.7c5016c0d871f3a47082.hot-update.js",
    "/js/app.a5111fef4770b6147e87.hot-update.js": "/js/app.a5111fef4770b6147e87.hot-update.js",
    "/js/settings-app.a5111fef4770b6147e87.hot-update.js": "/js/settings-app.a5111fef4770b6147e87.hot-update.js",
    "/js/app.74b0257cc2fdc7d04065.hot-update.js": "/js/app.74b0257cc2fdc7d04065.hot-update.js",
    "/js/app.4b1a083147da3776c23a.hot-update.js": "/js/app.4b1a083147da3776c23a.hot-update.js",
    "/js/app.6399bbe7af7094ef74d2.hot-update.js": "/js/app.6399bbe7af7094ef74d2.hot-update.js",
    "/js/app.ec86e5a3a5ab3397bb97.hot-update.js": "/js/app.ec86e5a3a5ab3397bb97.hot-update.js",
    "/js/app.7484b6758739264689e1.hot-update.js": "/js/app.7484b6758739264689e1.hot-update.js",
    "/js/app.28b4305d83d741609fdd.hot-update.js": "/js/app.28b4305d83d741609fdd.hot-update.js",
    "/js/app.01d306b961eb3ed078c4.hot-update.js": "/js/app.01d306b961eb3ed078c4.hot-update.js",
    "/js/app.e42a9a95a0e01c3e865b.hot-update.js": "/js/app.e42a9a95a0e01c3e865b.hot-update.js",
    "/js/app.5bf6565d3060f6a79e0c.hot-update.js": "/js/app.5bf6565d3060f6a79e0c.hot-update.js",
    "/js/app.5d9e4637adb32110c8bb.hot-update.js": "/js/app.5d9e4637adb32110c8bb.hot-update.js",
    "/js/app.03f59a273ec55d2ce13b.hot-update.js": "/js/app.03f59a273ec55d2ce13b.hot-update.js",
    "/js/settings-app.03f59a273ec55d2ce13b.hot-update.js": "/js/settings-app.03f59a273ec55d2ce13b.hot-update.js",
    "/js/app.503802e92d385ff31d58.hot-update.js": "/js/app.503802e92d385ff31d58.hot-update.js",
    "/js/app.81585e0510dcfe069c36.hot-update.js": "/js/app.81585e0510dcfe069c36.hot-update.js",
    "/js/app.58cbd60e56a4d715daa8.hot-update.js": "/js/app.58cbd60e56a4d715daa8.hot-update.js",
    "/js/app.f6bd04fec0fa8b28b480.hot-update.js": "/js/app.f6bd04fec0fa8b28b480.hot-update.js",
    "/js/app.3c8b05719a51c17c6de8.hot-update.js": "/js/app.3c8b05719a51c17c6de8.hot-update.js",
    "/js/app.3b102d4e5bcffa3a45a4.hot-update.js": "/js/app.3b102d4e5bcffa3a45a4.hot-update.js",
    "/js/app.66c7cf311d2dc4f2ad24.hot-update.js": "/js/app.66c7cf311d2dc4f2ad24.hot-update.js",
    "/js/app.87ed729f767a52735ec9.hot-update.js": "/js/app.87ed729f767a52735ec9.hot-update.js",
    "/js/app.d49f5dde159c2950a35c.hot-update.js": "/js/app.d49f5dde159c2950a35c.hot-update.js",
    "/js/app.73b19f73bc65257b3287.hot-update.js": "/js/app.73b19f73bc65257b3287.hot-update.js"
}
